README.rst
setup.py
src/cat/__init__.py
src/cat/cat.py
src/cat/catffi.py
src/cat/const.py
src/cat/container.py
src/cat/event.py
src/cat/heartbeat.py
src/cat/message.py
src/cat/messageid.py
src/cat/metric.py
src/cat/sdk.py
src/cat/transaction.py
src/cat/utils.py
src/cat/version.py
src/cat/lib/darwin/libcatclient.dylib
src/cat/lib/darwin/libcatclient_arm64.dylib
src/cat/lib/linux-glibc/libcatclient.so
src/cat/lib/linux-musl-libc/libcatclient.so
src/cat_zdm_sdk.egg-info/PKG-INFO
src/cat_zdm_sdk.egg-info/SOURCES.txt
src/cat_zdm_sdk.egg-info/dependency_links.txt
src/cat_zdm_sdk.egg-info/requires.txt
src/cat_zdm_sdk.egg-info/top_level.txt
test/test_all.py
test/test_event.py
test/test_message_id.py
test/test_metric.py
test/test_trans.py