Metadata-Version: 2.1
Name: cat-zdm-sdk
Version: 3.1.6
Summary: Cat SDK for Python
Home-page: https://github.com/dianping/cat/tree/master/lib/python
Author: Cat Team and Contributors
Author-email: cat@dianping.com
License: Apache License 2.0
Classifier: Development Status :: 4 - Beta
Classifier: Intended Audience :: Developers
Classifier: Programming Language :: Python :: 2
Classifier: Programming Language :: Python :: 2.7
Classifier: Programming Language :: Python :: 3
Classifier: Programming Language :: Python :: 3.5
Classifier: Programming Language :: Python :: 3.6
Requires-Dist: cffi<2.0,>=1.11
